LICENSE
MANIFEST.in
README.rst
kas-container
pyproject.toml
setup.py
kas/__init__.py
kas/__main__.py
kas/__version__.py
kas/attestation.py
kas/config.py
kas/configschema.py
kas/context.py
kas/includehandler.py
kas/kas.py
kas/kasusererror.py
kas/keyhandler.py
kas/libcmds.py
kas/libkas.py
kas/repos.py
kas/schema-kas.json
kas.egg-info/PKG-INFO
kas.egg-info/SOURCES.txt
kas.egg-info/dependency_links.txt
kas.egg-info/entry_points.txt
kas.egg-info/requires.txt
kas.egg-info/top_level.txt
kas/plugins/__init__.py
kas/plugins/build.py
kas/plugins/checkout.py
kas/plugins/clean.py
kas/plugins/diff.py
kas/plugins/dump.py
kas/plugins/for_all_repos.py
kas/plugins/lock.py
kas/plugins/menu.py
kas/plugins/shell.py
tests/test_build.py
tests/test_build_system.py
tests/test_commands.py
tests/test_environment_variables.py
tests/test_includehandler.py
tests/test_layers.py
tests/test_menu.py
tests/test_patch.py
tests/test_refspec.py
tests/test_signature_verify.py
tests/test_transitive_includes.py