Metadata-Version: 2.4
Name: kas
Version: 5.1
Summary: Setup tool for bitbake based projects
Maintainer-email: Jan Kiszka <jan.kiszka@siemens.com>
License: MIT
Project-URL: Documentation, https://kas.readthedocs.io/
Project-URL: Homepage, https://github.com/siemens/kas
Project-URL: Repository, https://github.com/siemens/kas.git
Keywords: OpenEmbedded bitbake development
Classifier: Development Status :: 5 - Production/Stable
Classifier: Intended Audience :: Developers
Classifier: License :: OSI Approved :: MIT License
Classifier: Programming Language :: Python :: 3 :: Only
Classifier: Programming Language :: Python :: 3.9
Classifier: Programming Language :: Python :: 3.10
Classifier: Programming Language :: Python :: 3.11
Classifier: Programming Language :: Python :: 3.12
Classifier: Programming Language :: Python :: 3.13
Classifier: Programming Language :: Python :: 3.14
Classifier: Topic :: Software Development :: Build Tools
Requires-Python: >=3.9
License-File: LICENSE
Requires-Dist: distro<2,>=1
Requires-Dist: gitpython<4,>=3.1
Requires-Dist: jsonschema<5,>=3.2
Requires-Dist: pyyaml<7,>=3
Provides-Extra: tui
Requires-Dist: kconfiglib<15,>=14.1; extra == "tui"
Provides-Extra: verify
Requires-Dist: python-gnupg<1,>=0.4.0; extra == "verify"
Provides-Extra: test
Requires-Dist: kas[tui]; extra == "test"
Requires-Dist: kas[verify]; extra == "test"
Requires-Dist: pytest<9,>=6; extra == "test"
Dynamic: license-file
